src/uart_rx/uart_rx.v
module uart_rx #(
    parameter DATA_WIDTH = 8
) (
    input logic din,            // Serial input
    input logic clk,
    input logic reset,
    output logic [DATA_WIDTH-1:0] par_out  // Parallel output
);
    logic en_shift; 
    logic [2:0] state;  
    logic flag;
    logic [DATA_WIDTH-1:0] shift_reg;
    logic [3:0] bit_counter;
    
    // Define states
    localparam IDLE  = 3'b000;
    localparam START = 3'b001;
    localparam DATA  = 3'b010;
    localparam STOP  = 3'b011;

    always @(posedge clk or negedge reset) begin
        if(!reset) begin
            state <= IDLE;
            shift_reg <= 0;
            bit_counter <= 0;
            par_out <= 0;
        end else begin
            case(state)
                IDLE: begin
                    if(!din) begin  // Start bit detection (low)
                        state <= START;
                        bit_counter <= 0;
                    end
                end
                
                START: begin
                    // Wait 1.5 bit times (middle of first data bit)
                    state <= DATA;
                end
                
                DATA: begin
                    shift_reg <= {din, shift_reg[DATA_WIDTH-1:1]};
                    bit_counter <= bit_counter + 1;
                    if(bit_counter == DATA_WIDTH-1)
                        state <= STOP;
                end
                
                STOP: begin
                    par_out <= shift_reg;
                    state <= IDLE;
                end
            endcase
        end
    end
endmodule

src/uart_rx/uart_rx_tb.v
module tb_uart_rx;
    parameter DATA_WIDTH = 8;
    
    logic din;
    logic clk = 0;
    logic reset;
    logic [DATA_WIDTH-1:0] par_out;

    uart_rx #(DATA_WIDTH) DUT (
        .din(din),
        .clk(clk),
        .reset(reset),
        .par_out(par_out)
    );

    localparam CLK_PERIOD = 10;
    always #(CLK_PERIOD/2) clk = ~clk;

    initial begin
        $dumpfile("tb_uart_rx.vcd");
        $dumpvars(0, tb_uart_rx);
        
        reset = 0;
        #20 reset = 1;
        
        // Send a byte (LSB first)
        din = 1; // idle
        #100;
        
        // Start bit
        din = 0;
        #160;
        
        // Data bits (0x55 - 01010101)
        din = 1; #160; // bit 0
        din = 0; #160; // bit 1
        din = 1; #160; // bit 2
        din = 0; #160; // bit 3
        din = 1; #160; // bit 4
        din = 0; #160; // bit 5
        din = 1; #160; // bit 6
        din = 0; #160; // bit 7
        
        // Stop bit
        din = 1;
        #160;
        
        $display("Received data: %h", par_out);
        $finish;
    end
endmodule

src/uart_rx/tb_uart_rx.vcd
$date
	Thu May 15 21:16:36 2025
$end
$version
	Icarus Verilog
$end
$timescale
	1s
$end
$scope module tb_uart_rx $end
$var wire 8 ! par_out [7:0] $end
$var parameter 32 " CLK_PERIOD $end
$var parameter 32 # DATA_WIDTH $end
$var reg 1 $ clk $end
$var reg 1 % din $end
$var reg 1 & reset $end
$scope module DUT $end
$var wire 1 $ clk $end
$var wire 1 % din $end
$var wire 1 & reset $end
$var parameter 3 ' DATA $end
$var parameter 32 ( DATA_WIDTH $end
$var parameter 3 ) IDLE $end
$var parameter 3 * START $end
$var parameter 3 + STOP $end
$var reg 4 , bit_counter [3:0] $end
$var reg 8 - par_out [7:0] $end
$var reg 8 . shift_reg [7:0] $end
$var reg 3 / state [2:0] $end
$upscope $end
$upscope $end
$enddefinitions $end
$comment Show the parameter values. $end
$dumpall
b11 +
b1 *
b0 )
b1000 (
b10 '
b1000 #
b1010 "
$end
#0
$dumpvars
b0 /
b0 .
b0 -
b0 ,
0&
x%
0$
b0 !
$end
#5
1$
#10
0$
#15
1$
#20
0$
1%
1&
#25
1$
#30
0$
#35
1$
#40
0$
#45
1$
#50
0$
#55
1$
#60
0$
#65
1$
#70
0$
#75
1$
#80
0$
#85
1$
#90
0$
#95
1$
#100
0$
#105
1$
#110
0$
#115
1$
#120
0$
0%
#125
b1 /
1$
#130
0$
#135
b10 /
1$
#140
0$
#145
b1 ,
1$
#150
0$
#155
b10 ,
1$
#160
0$
#165
b11 ,
1$
#170
0$
#175
b100 ,
1$
#180
0$
#185
b101 ,
1$
#190
0$
#195
b110 ,
1$
#200
0$
#205
b111 ,
1$
#210
0$
#215
b11 /
b1000 ,
1$
#220
0$
#225
b0 /
1$
#230
0$
#235
b0 ,
b1 /
1$
#240
0$
#245
b10 /
1$
#250
0$
#255
b1 ,
1$
#260
0$
#265
b10 ,
1$
#270
0$
#275
b11 ,
1$
#280
0$
1%
#285
b100 ,
b10000000 .
1$
#290
0$
#295
b101 ,
b11000000 .
1$
#300
0$
#305
b110 ,
b11100000 .
1$
#310
0$
#315
b111 ,
b11110000 .
1$
#320
0$
#325
b11 /
b1000 ,
b11111000 .
1$
#330
0$
#335
b0 /
b11111000 !
b11111000 -
1$
#340
0$
#345
1$
#350
0$
#355
1$
#360
0$
#365
1$
#370
0$
#375
1$
#380
0$
#385
1$
#390
0$
#395
1$
#400
0$
#405
1$
#410
0$
#415
1$
#420
0$
#425
1$
#430
0$
#435
1$
#440
0$
0%
#445
b0 ,
b1 /
1$
#450
0$
#455
b10 /
1$
#460
0$
#465
b1 ,
b1111100 .
1$
#470
0$
#475
b10 ,
b111110 .
1$
#480
0$
#485
b11 ,
b11111 .
1$
#490
0$
#495
b100 ,
b1111 .
1$
#500
0$
#505
b101 ,
b111 .
1$
#510
0$
#515
b110 ,
b11 .
1$
#520
0$
#525
b111 ,
b1 .
1$
#530
0$
#535
b11 /
b1000 ,
b0 .
1$
#540
0$
#545
b0 /
b0 !
b0 -
1$
#550
0$
#555
b0 ,
b1 /
1$
#560
0$
#565
b10 /
1$
#570
0$
#575
b1 ,
1$
#580
0$
#585
b10 ,
1$
#590
0$
#595
b11 ,
1$
#600
0$
1%
#605
b100 ,
b10000000 .
1$
#610
0$
#615
b101 ,
b11000000 .
1$
#620
0$
#625
b110 ,
b11100000 .
1$
#630
0$
#635
b111 ,
b11110000 .
1$
#640
0$
#645
b11 /
b1000 ,
b11111000 .
1$
#650
0$
#655
b0 /
b11111000 !
b11111000 -
1$
#660
0$
#665
1$
#670
0$
#675
1$
#680
0$
#685
1$
#690
0$
#695
1$
#700
0$
#705
1$
#710
0$
#715
1$
#720
0$
#725
1$
#730
0$
#735
1$
#740
0$
#745
1$
#750
0$
#755
1$
#760
0$
0%
#765
b0 ,
b1 /
1$
#770
0$
#775
b10 /
1$
#780
0$
#785
b1 ,
b1111100 .
1$
#790
0$
#795
b10 ,
b111110 .
1$
#800
0$
#805
b11 ,
b11111 .
1$
#810
0$
#815
b100 ,
b1111 .
1$
#820
0$
#825
b101 ,
b111 .
1$
#830
0$
#835
b110 ,
b11 .
1$
#840
0$
#845
b111 ,
b1 .
1$
#850
0$
#855
b11 /
b1000 ,
b0 .
1$
#860
0$
#865
b0 /
b0 !
b0 -
1$
#870
0$
#875
b0 ,
b1 /
1$
#880
0$
#885
b10 /
1$
#890
0$
#895
b1 ,
1$
#900
0$
#905
b10 ,
1$
#910
0$
#915
b11 ,
1$
#920
0$
1%
#925
b100 ,
b10000000 .
1$
#930
0$
#935
b101 ,
b11000000 .
1$
#940
0$
#945
b110 ,
b11100000 .
1$
#950
0$
#955
b111 ,
b11110000 .
1$
#960
0$
#965
b11 /
b1000 ,
b11111000 .
1$
#970
0$
#975
b0 /
b11111000 !
b11111000 -
1$
#980
0$
#985
1$
#990
0$
#995
1$
#1000
0$
#1005
1$
#1010
0$
#1015
1$
#1020
0$
#1025
1$
#1030
0$
#1035
1$
#1040
0$
#1045
1$
#1050
0$
#1055
1$
#1060
0$
#1065
1$
#1070
0$
#1075
1$
#1080
0$
0%
#1085
b0 ,
b1 /
1$
#1090
0$
#1095
b10 /
1$
#1100
0$
#1105
b1 ,
b1111100 .
1$
#1110
0$
#1115
b10 ,
b111110 .
1$
#1120
0$
#1125
b11 ,
b11111 .
1$
#1130
0$
#1135
b100 ,
b1111 .
1$
#1140
0$
#1145
b101 ,
b111 .
1$
#1150
0$
#1155
b110 ,
b11 .
1$
#1160
0$
#1165
b111 ,
b1 .
1$
#1170
0$
#1175
b11 /
b1000 ,
b0 .
1$
#1180
0$
#1185
b0 /
b0 !
b0 -
1$
#1190
0$
#1195
b0 ,
b1 /
1$
#1200
0$
#1205
b10 /
1$
#1210
0$
#1215
b1 ,
1$
#1220
0$
#1225
b10 ,
1$
#1230
0$
#1235
b11 ,
1$
#1240
0$
1%
#1245
b100 ,
b10000000 .
1$
#1250
0$
#1255
b101 ,
b11000000 .
1$
#1260
0$
#1265
b110 ,
b11100000 .
1$
#1270
0$
#1275
b111 ,
b11110000 .
1$
#1280
0$
#1285
b11 /
b1000 ,
b11111000 .
1$
#1290
0$
#1295
b0 /
b11111000 !
b11111000 -
1$
#1300
0$
#1305
1$
#1310
0$
#1315
1$
#1320
0$
#1325
1$
#1330
0$
#1335
1$
#1340
0$
#1345
1$
#1350
0$
#1355
1$
#1360
0$
#1365
1$
#1370
0$
#1375
1$
#1380
0$
#1385
1$
#1390
0$
#1395
1$
#1400
0$
0%
#1405
b0 ,
b1 /
1$
#1410
0$
#1415
b10 /
1$
#1420
0$
#1425
b1 ,
b1111100 .
1$
#1430
0$
#1435
b10 ,
b111110 .
1$
#1440
0$
#1445
b11 ,
b11111 .
1$
#1450
0$
#1455
b100 ,
b1111 .
1$
#1460
0$
#1465
b101 ,
b111 .
1$
#1470
0$
#1475
b110 ,
b11 .
1$
#1480
0$
#1485
b111 ,
b1 .
1$
#1490
0$
#1495
b11 /
b1000 ,
b0 .
1$
#1500
0$
#1505
b0 /
b0 !
b0 -
1$
#1510
0$
#1515
b0 ,
b1 /
1$
#1520
0$
#1525
b10 /
1$
#1530
0$
#1535
b1 ,
1$
#1540
0$
#1545
b10 ,
1$
#1550
0$
#1555
b11 ,
1$
#1560
0$
1%
#1565
b100 ,
b10000000 .
1$
#1570
0$
#1575
b101 ,
b11000000 .
1$
#1580
0$
#1585
b110 ,
b11100000 .
1$
#1590
0$
#1595
b111 ,
b11110000 .
1$
#1600
0$
#1605
b11 /
b1000 ,
b11111000 .
1$
#1610
0$
#1615
b0 /
b11111000 !
b11111000 -
1$
